Workbook

Sheet Data_Sources
A1: Ashok Leyland Limited - Credit Assessment: Data Sources Used (Assignment Point 3)
A2: Company: Ashok Leyland Ltd (NSE: ASHOKLEY), Hinduja Group flagship; commercial-vehicle OEM. Basis: STANDALONE financial statements, ₹ crore, FY24-FY26 (years ending 31 March). Sources: Annual Reports 2023-24, 2024-25 and 2025-26 (uploaded). Page numbers are the printed page numbers of each annual report.
A4: Source | B4: What was extracted | C4: Where (printed pages) | D4: Key evidence found | E4: Why it matters for credit | F4: Workbook sheet
A5: 1. Latest annual report + two prior years (FY24, FY25, FY26) | B5: Revenue, EBITDA, PAT, borrowings, lease liabilities, finance cost (with break-up), CFO, capex, dividends, tax paid, full balance sheet | C5: FY26 AR: BS p.122, P&L p.123, CF p.124-125, Note 2.5 p.169 FY25 AR: BS p.112, P&L p.113, CF p.114-115, Note 2.5 p.158 FY24 AR: BS p.116, P&L p.117, CF p.118-119 | D5: Revenue ₹38,367 cr → ₹38,753 cr → ₹44,007 cr; PAT ₹2,618 cr → ₹3,303 cr → ₹3,566 cr. Total debt incl. leases fell from ₹2,299 cr to ₹1,195 cr while cash and liquid investments rose, turning the company net-cash. Reported CFO (₹2,503 / ₹7,819 / ₹4,792 cr) is distorted by a ₹1,453 cr interim-dividend bank-account swing between FY24 and FY25, so an adjusted CFO is used. Capex doubled from ₹496 cr to ₹1,050 cr. FY26 PAT absorbed a one-off ₹308 cr labour-code charge. | E5: A three-year trend shows whether deleveraging and margin gains are structural or one-off; adjustments remove timing distortions before ratios are read. | F5: Financials, Ratios
A6: 2. Management Discussion & Analysis | B6: Industry volumes and outlook, demand drivers, market share, competition, stated risks and threats | C6: FY26 AR p.52-58 (industry table p.54, risk section p.56-57) FY25 AR p.48 onward FY24 AR p.60 onward | D6: Domestic CV industry hit a record ~10.8 lakh units in FY26 (+12.6%), with a weak H1 and a strong H2 after the GST cut on CVs from 28% to 18% (Sept-2025). Ashok Leyland's M&HCV share slipped from 31.1% (FY24) to 30.7% (FY25) to 30.3% (FY26); it leads buses (~34%) and hit a record LCV share (Vahan 12.7%). Exports rose 18.5% to 18,082 units; aftermarket revenue about ₹4,450 cr. Management flags West Asia/crude risk, tariffs, emission-compliance costs, electric 3-wheeler substitution in LCVs, volatile export markets and delays in government capex. MHCV truck volumes were flat for three years before FY26, which confirms cyclicality. | E6: Places the ratios in the CV cycle: FY26 is an up-cycle year, so leverage headroom must be tested against a downturn. | F6: Data_Sources (qualitative), Financials memo
A7: 3. Notes to Accounts | B7: Borrowings by instrument, security, repayment terms, current maturities, covenants, contingent liabilities, guarantees, commitments, related-party dealings | C7: FY26 AR: Notes 1.16 p.161, 1.21 p.163, 1.11B p.157, 3.8 RPT p.193-199, 3.9 p.200-201, 3.10 p.201, 3.11-3.12 p.202-203 FY25 AR: 1.16 p.151, 1.21 p.153, 3.8 p.181, 3.9 p.188-189, 3.11 p.190 FY24 AR: 1.16 p.154, 1.21 p.156, 3.9 p.187, 3.11 p.188 | D7: FY26 debt consists only of secured bank term loans, one ₹200 cr 7.30% NCD (bullet 17-Mar-2027), a ₹150 cr short-term loan and an interest-free sales-tax loan; the weighted cost is 6.83%. All covenants were met, and they include rating and promoter-holding triggers. Contingent liabilities are modest at ₹343 cr, mostly indirect-tax disputes. Guarantees for subsidiaries total ₹786 cr, mainly Switch Mobility UK (₹633 cr), whose UK manufacturing was discontinued in FY26. Continuing support to loss-making EV subsidiaries: ₹499 cr application money to Optare (FY25) and a ₹371 cr investment (FY26). Related-party items include ICDs to Hinduja group entities (up to ₹100 cr each during FY26, nil at year-end), dividends of ₹933 cr to the promoter, and an unquantified End-of-Life-Vehicle EPR obligation. | E7: The notes carry the strongest credit evidence: hidden obligations, security, covenant triggers and group cash leakage that the headline ratios do not show. | F7: Debt_Analysis (A, F, H), Ratios §7
A8: 4. Financial risk / liquidity disclosure (Note 3.6) | B8: Contractual maturity bands, undrawn lines, CP headroom, fixed/floating mix, rate sensitivity, FX exposure and hedging | C8: FY26 AR: capital mgmt p.183, FX p.183-185, interest rate p.186, liquidity p.187-188 FY25 AR p.171-176 FY24 AR p.172-176 | D8: Borrowing outflows due within 1 year: ₹1,234 cr (FY24), ₹614 cr (FY25), ₹698 cr (FY26). FY26 has undrawn bank lines of ₹2,854 cr plus a ₹2,000 cr CP option. Floating-rate debt is only ₹403 cr, and a 25 bp move changes profit by about ₹1 cr. Net FX exposure is small and largely hedged with forwards. | E8: Shows refinancing and liquidity risk: whether near-term maturities can be met from cash and lines without market access. | F8: Debt_Analysis (B, C, D, G)
A9: 5. Consolidated financial statements (supplementary) | B9: Group borrowings, equity, finance cost; structure of Hinduja Leyland Finance (HLF) | C9: FY26 AR p.220-221, Board's Report p.22 (HLF-NDL merger scheme) FY25 AR p.208-209 | D9: Consolidated borrowings of about ₹63,650 cr (FY26) are overwhelmingly HLF's NBFC debt, against standalone borrowings of about ₹1,152 cr. A scheme to merge HLF into NDL Ventures is awaiting NCLT approval. | E9: Justifies standalone analysis and highlights group-support and contagion risk. | F9: Consolidated_View
A10: 6. CRA rationale (after own view only) | B10: Strengths, weaknesses, rating sensitivities, liquidity view | C10: Not consulted yet - deliberately, per integrity rule | D10: To be read only after the independent assessment and lending decision are finished, and used only for the one-page comparison. | E10: Tests own judgement against the agency's view; not a source for copying. | F10: Later stage
A12: Workbook legend
A13: Blue text | B13: Hard-coded input copied from the annual report (source given beside it)
A14: Black text | B14: Formula / calculation
A15: Green text | B15: Link pulled from another sheet
A16: Check rows | B16: Rows labelled 'Check' should show '-' (zero); they tie extracted numbers back to report totals
A18: Sheets
A19: Financials | B19: Three-year extracted P&L, balance sheet, cash flow, finance-cost break-up, adjustments and memo items
A20: Ratios | B20: Profitability, leverage, coverage, cash-flow, liquidity, working-capital and off-balance-sheet ratios with trend flags
A21: Debt_Analysis | B21: Borrowings by instrument, debt mix, maturity bands, liquidity cover, contingent liabilities, FX, FY26 repayment schedule
A22: Consolidated_View | B22: Why standalone is used - group borrowings dominated by the NBFC subsidiary

Sheet Financials
A1: Ashok Leyland Limited - Standalone Financial Data Extracted (₹ crore)
A2: Blue = hard-coded input taken from the annual report; Black = formula. FY24 figures are the comparatives reported in the FY25 annual report (checked against the FY24 annual report, no restatement). FY25 figures are the comparatives in the FY26 annual report.
B4: Particulars (₹ crore) | C4: FY24 | D4: FY25 | E4: FY26 | F4: Source (Annual Report, Note, printed page)
A5: A. STATEMENT OF PROFIT AND LOSS
B6: Revenue from operations | C6: 38367.03 | D6: 38752.74 | E6: 44007.03 | F6: Statement of P&L - FY26 AR p.123; FY25 AR p.113; FY24 AR p.117
B7: Other income | C7: 246.57 | D7: 250.25 | E7: 315.17 | F7: Statement of P&L (Note 2.2)
B8: Cost of materials and services consumed | C8: 26916.54 | D8: 25711.74 | E8: 29722.68 | F8: Statement of P&L
B9: Purchases of stock-in-trade | C9: 1506.41 | D9: 1680.46 | E9: 1805.39 | F9: Statement of P&L
B10: Changes in inventories of FG, SIT and WIP | C10: -510.94 | D10: 230.58 | E10: -110.93 | F10: Statement of P&L (Note 2.3)
B11: Cost of goods sold (sum of above three) | C11: =SUM(C8:C10) -> 27912.01 | D11: =SUM(D8:D10) -> 27622.78 | E11: =SUM(E8:E10) -> 31417.14
B12: Employee benefits expense | C12: 2233.38 | D12: 2406.27 | E12: 2606.69 | F12: Statement of P&L (Note 2.4)
B13: Other expenses | C13: 3615.06 | D13: 3793.13 | E13: 4250.95 | F13: Statement of P&L (Note 2.7)
B14: Finance costs (as reported) | C14: 249.44 | D14: 216.91 | E14: 169.73 | F14: Statement of P&L (Note 2.5) - FY26 AR p.169; FY25 AR p.158
B15: Depreciation and amortisation expense | C15: 717.81 | D15: 719.34 | E15: 715.19 | F15: Statement of P&L (Note 2.6)
B16: Profit before exceptional items and tax | C16: 3885.9 | D16: 4244.56 | E16: 5162.5 | F16: Statement of P&L
B17: Exceptional items | C17: -93.72 | D17: 103.73 | E17: -348.48 | F17: Note 2.8 - FY26: labour-code impact (308.48) + litigation (40.00); FY25: fair-value gain on Hinduja Energy 120.53 - FY26 AR p.172; FY25 AR p.160
B18: Profit before tax | C18: 3792.18 | D18: 4348.29 | E18: 4814.02 | F18: Statement of P&L
B19: Total tax expense | C19: 1174.31 | D19: 1045 | E19: 1248.49 | F19: Statement of P&L
B20: Profit for the year (PAT) | C20: 2617.87 | D20: 3303.29 | E20: 3565.53 | F20: Statement of P&L
A22: B. DERIVED EARNINGS MEASURES (formulas)
B23: EBITDA (Revenue - COGS - Employee - Other expenses; excludes other income) | C23: =C6-C11-C12-C13 -> 4606.58 | D23: =D6-D11-D12-D13 -> 4930.56 | E23: =E6-E11-E12-E13 -> 5732.25 | F23: Operating EBITDA - other income excluded to keep treasury income out of debt-servicing capacity
B24: EBITDA including other income | C24: =C23+C7 -> 4853.15 | D24: =D23+D7 -> 5180.81 | E24: =E23+E7 -> 6047.42
B25: EBIT (EBITDA - D&A) | C25: =C23-C15 -> 3888.77 | D25: =D23-D15 -> 4211.22 | E25: =E23-E15 -> 5017.06
B26: Check: EBITDA + OI - D&A - FC should equal PBT before exceptional (0 = OK) | C26: =ROUND(C23+C7-C15-C14-C16,2) -> 0 | D26: =ROUND(D23+D7-D15-D14-D16,2) -> 0 | E26: =ROUND(E23+E7-E15-E14-E16,2) -> 0
A28: C. FINANCE COST BREAK-UP (Note 2.5)
B29: Interest expense (gross, before capitalisation) | C29: 192.66 | D29: 142.25 | E29: 91.29 | F29: Note 2.5 - FY26 AR p.169; FY25 AR p.158
B30: Less: interest capitalised | C30: 2.3 | D30: 17.36 | E30: 21.24 | F30: Note 2.5
B31: Unwinding of discount on provisions (non-cash) | C31: 55.36 | D31: 88.55 | E31: 95.69 | F31: Note 2.5 - relates to warranty/other provisions, not debt
B32: Interest on lease liability | C32: 3.72 | D32: 3.47 | E32: 3.99 | F32: Note 2.5
B33: Check: break-up less reported finance cost (0 = OK) | C33: =ROUND(C29-C30+C31+C32-C14,2) -> 0 | D33: =ROUND(D29-D30+D31+D32-D14,2) -> 0 | E33: =ROUND(E29-E30+E31+E32-E14,2) -> 0
A35: D. BALANCE SHEET (as at 31 March)
B36: Property, plant and equipment | C36: 4502.22 | D36: 4406.64 | E36: 5072.1 | F36: Balance Sheet - FY26 AR p.122; FY25 AR p.112; FY24 AR p.116
B37: Capital work-in-progress | C37: 95.53 | D37: 276.87 | E37: 209.98 | F37: Balance Sheet - FY26 AR p.122; FY25 AR p.112; FY24 AR p.116
B38: Right-of-use asset | C38: 235.3 | D38: 275.33 | E38: 263.04 | F38: Balance Sheet - FY26 AR p.122; FY25 AR p.112; FY24 AR p.116
B39: Goodwill | C39: 449.9 | D39: 449.9 | E39: 449.9 | F39: Balance Sheet - FY26 AR p.122; FY25 AR p.112; FY24 AR p.116
B40: Other intangible assets | C40: 764.38 | D40: 713.62 | E40: 603.83 | F40: Balance Sheet - FY26 AR p.122; FY25 AR p.112; FY24 AR p.116
B41: Intangible assets under development | C41: 106 | D41: 147.89 | E41: 269.31 | F41: Balance Sheet - FY26 AR p.122; FY25 AR p.112; FY24 AR p.116
B42: Non-current investments (mainly subsidiaries/JVs incl. Hinduja Leyland Finance) | C42: 5310.71 | D42: 5654.26 | E42: 6559.29 | F42: Balance Sheet - FY26 AR p.122; FY25 AR p.112; FY24 AR p.116 (Note 1.3)
B43: Non-current trade receivables | C43: 0.25 | D43: 0 | E43: 0 | F43: Balance Sheet - FY26 AR p.122; FY25 AR p.112; FY24 AR p.116
B44: Non-current other financial assets | C44: 64.94 | D44: 575.01 | E44: 128.4 | F44: Balance Sheet - FY26 AR p.122; FY25 AR p.112; FY24 AR p.116
B45: Income tax assets (net) | C45: 50.34 | D45: 34.32 | E45: 14.53 | F45: Balance Sheet - FY26 AR p.122; FY25 AR p.112; FY24 AR p.116
B46: Other non-current assets | C46: 369.09 | D46: 659.69 | E46: 361.29 | F46: Balance Sheet - FY26 AR p.122; FY25 AR p.112; FY24 AR p.116
B47: Total non-current assets | C47: =SUM(C36:C46) -> 11948.66 | D47: =SUM(D36:D46) -> 13193.53 | E47: =SUM(E36:E46) -> 13931.67
B48: Inventories | C48: 3190.69 | D48: 2957.32 | E48: 3486.02 | F48: Balance Sheet - FY26 AR p.122; FY25 AR p.112; FY24 AR p.116
B49: Current investments (liquid mutual funds) | C49: 249.06 | D49: 3018.7 | E49: 4119.71 | F49: Balance Sheet - FY26 AR p.122; FY25 AR p.112; FY24 AR p.116 (Note 1.9)
B50: Trade receivables | C50: 3569.65 | D50: 2887.32 | E50: 2950.41 | F50: Balance Sheet - FY26 AR p.122; FY25 AR p.112; FY24 AR p.116
B51: Cash and cash equivalents | C51: 1941.87 | D51: 2659.82 | E51: 2031.09 | F51: Balance Sheet - FY26 AR p.122; FY25 AR p.112; FY24 AR p.116
B52: Bank balances other than cash and cash equivalents | C52: 1496.31 | D52: 46.13 | E52: 945.96 | F52: Balance Sheet - FY26 AR p.122; FY25 AR p.112; FY24 AR p.116 (Note 1.11B)
B53: Current loans | C53: 95 | D53: 0 | E53: 0 | F53: Balance Sheet - FY26 AR p.122; FY25 AR p.112; FY24 AR p.116
B54: Other current financial assets | C54: 241.8 | D54: 118.21 | E54: 242.94 | F54: Balance Sheet - FY26 AR p.122; FY25 AR p.112; FY24 AR p.116
B55: Other current assets | C55: 812.69 | D55: 621.12 | E55: 885.86 | F55: Balance Sheet - FY26 AR p.122; FY25 AR p.112; FY24 AR p.116
B56: Total current assets | C56: =SUM(C48:C55) -> 11597.07 | D56: =SUM(D48:D55) -> 12308.62 | E56: =SUM(E48:E55) -> 14661.99
B57: Assets classified as held for sale | C57: 66.02 | D57: 23.68 | E57: 0 | F57: Balance Sheet - FY26 AR p.122; FY25 AR p.112; FY24 AR p.116
B58: TOTAL ASSETS | C58: =C47+C56+C57 -> 23611.75 | D58: =D47+D56+D57 -> 25525.83 | E58: =E47+E56+E57 -> 28593.66
B59: Equity share capital | C59: 293.63 | D59: 293.65 | E59: 587.39 | F59: Balance Sheet - FY26 AR p.122; FY25 AR p.112; FY24 AR p.116 (FY26: 1:1 bonus issue)
B60: Other equity | C60: 8516.74 | D60: 11225.14 | E60: 12526.03 | F60: Balance Sheet - FY26 AR p.122; FY25 AR p.112; FY24 AR p.116
B61: Total equity (Net worth) | C61: =C59+C60 -> 8810.37 | D61: =D59+D60 -> 11518.79 | E61: =E59+E60 -> 13113.42
B62: Non-current borrowings | C62: 1131.64 | D62: 902.23 | E62: 517.88 | F62: Balance Sheet - FY26 AR p.122; FY25 AR p.112; FY24 AR p.116 (Note 1.16)
B63: Non-current lease liabilities | C63: 29.4 | D63: 31.74 | E63: 29.6 | F63: Balance Sheet - FY26 AR p.122; FY25 AR p.112; FY24 AR p.116
B64: Non-current other financial liabilities | C64: 21.31 | D64: 12.57 | E64: 10.99 | F64: Balance Sheet - FY26 AR p.122; FY25 AR p.112; FY24 AR p.116
B65: Non-current contract liabilities | C65: 283.45 | D65: 372.86 | E65: 423.97 | F65: Balance Sheet - FY26 AR p.122; FY25 AR p.112; FY24 AR p.116
B66: Non-current provisions | C66: 724.07 | D66: 708.97 | E66: 635.45 | F66: Balance Sheet - FY26 AR p.122; FY25 AR p.112; FY24 AR p.116
B67: Deferred tax liabilities (net) | C67: 556.31 | D67: 547.89 | E67: 535.71 | F67: Balance Sheet - FY26 AR p.122; FY25 AR p.112; FY24 AR p.116
B68: Total non-current liabilities | C68: =SUM(C62:C67) -> 2746.18 | D68: =SUM(D62:D67) -> 2576.26 | E68: =SUM(E62:E67) -> 2153.6
B69: Current borrowings (incl. current maturities of long-term debt) | C69: 1122.89 | D69: 533.21 | E69: 633.82 | F69: Balance Sheet - FY26 AR p.122; FY25 AR p.112; FY24 AR p.116 (Note 1.21)
B70: Current lease liabilities | C70: 15.47 | D70: 14.54 | E70: 13.74 | F70: Balance Sheet - FY26 AR p.122; FY25 AR p.112; FY24 AR p.116
B71: Trade payables - MSME | C71: 79.54 | D71: 56.58 | E71: 231.08 | F71: Balance Sheet - FY26 AR p.122; FY25 AR p.112; FY24 AR p.116
B72: Trade payables - others | C72: 6225.65 | D72: 7248.11 | E72: 8098.18 | F72: Balance Sheet - FY26 AR p.122; FY25 AR p.112; FY24 AR p.116
B73: Other current financial liabilities | C73: 2463.77 | D73: 1211.22 | E73: 1365.79 | F73: Balance Sheet - FY26 AR p.122; FY25 AR p.112; FY24 AR p.116 (Note 1.23) - FY24 includes ₹1,453.48 cr interim dividend payable
B74: Current contract liabilities | C74: 476.02 | D74: 422.85 | E74: 674.11 | F74: Balance Sheet - FY26 AR p.122; FY25 AR p.112; FY24 AR p.116
B75: Current provisions | C75: 650.68 | D75: 825.15 | E75: 1350.34 | F75: Balance Sheet - FY26 AR p.122; FY25 AR p.112; FY24 AR p.116
B76: Other current liabilities | C76: 478.11 | D76: 492.78 | E76: 219.02 | F76: Balance Sheet - FY26 AR p.122; FY25 AR p.112; FY24 AR p.116
B77: Current tax liabilities (net) | C77: 526.24 | D77: 621.69 | E77: 740.56 | F77: Balance Sheet - FY26 AR p.122; FY25 AR p.112; FY24 AR p.116
B78: Total current liabilities | C78: =SUM(C69:C77) -> 12038.37 | D78: =SUM(D69:D77) -> 11426.13 | E78: =SUM(E69:E77) -> 13326.64
B79: Liabilities associated with assets held for sale | C79: 16.83 | D79: 4.65 | E79: 0 | F79: Balance Sheet - FY26 AR p.122; FY25 AR p.112; FY24 AR p.116
B80: TOTAL EQUITY AND LIABILITIES | C80: =C61+C68+C78+C79 -> 23611.75 | D80: =D61+D68+D78+D79 -> 25525.83 | E80: =E61+E68+E78+E79 -> 28593.66
B81: Check: Total assets - Total equity & liabilities (0 = OK) | C81: =ROUND(C58-C80,2) -> 0 | D81: =ROUND(D58-D80,2) -> 0 | E81: =ROUND(E58-E80,2) -> 0
A83: E. ADJUSTMENTS FROM NOTES
B84: Earmarked bank balances (unclaimed/unpaid dividend, escrow) - not free liquidity | C84: 1496.31 | D84: 46.13 | E84: 45.96 | F84: Note 1.11B - FY26 AR p.157; FY25 AR p.146 (FY24: incl. ₹1,453.48 cr interim-dividend account)
B85: Total trade payables | C85: =C71+C72 -> 6305.19 | D85: =D71+D72 -> 7304.69 | E85: =E71+E72 -> 8329.26
B86: Total lease liabilities | C86: =C63+C70 -> 44.87 | D86: =D63+D70 -> 46.28 | E86: =E63+E70 -> 43.34
B87: Total borrowings (non-current + current) | C87: =C62+C69 -> 2254.53 | D87: =D62+D69 -> 1435.44 | E87: =E62+E69 -> 1151.7
B88: Total debt incl. lease liabilities | C88: =C87+C86 -> 2299.4 | D88: =D87+D86 -> 1481.72 | E88: =E87+E86 -> 1195.04
B89: Unencumbered cash & liquid investments | C89: =C51+C49+C52-C84 -> 2190.93 | D89: =D51+D49+D52-D84 -> 5678.52 | E89: =E51+E49+E52-E84 -> 7050.8 | F89: Cash + current investments + other bank balances - earmarked balances
B90: Tangible net worth (Equity - goodwill - intangibles - IAUD) | C90: =C61-C39-C40-C41 -> 7490.09 | D90: =D61-D39-D40-D41 -> 10207.38 | E90: =E61-E39-E40-E41 -> 11790.38
B91: Total outside liabilities (Total assets - Equity) | C91: =C58-C61 -> 14801.38 | D91: =D58-D61 -> 14007.04 | E91: =E58-E61 -> 15480.24
A93: F. CASH FLOW STATEMENT
B94: Net cash from operating activities (CFO, as reported) | C94: 2503.12 | D94: 7819.42 | E94: 4792.1 | F94: Cash Flow Statement - FY26 AR p.124-125; FY25 AR p.114-115; FY24 AR p.118-119
B95: of which: movement in interim-dividend designated bank account | C95: -1453.48 | D95: 1453.48 | E95: 0 | F95: Cash Flow Statement - FY26 AR p.124-125; FY25 AR p.114-115; FY24 AR p.118-119 - one-off timing item (FY24 dividend paid in FY25)
B96: Adjusted CFO (excluding dividend-account movement) | C96: =C94-C95 -> 3956.6 | D96: =D94-D95 -> 6365.94 | E96: =E94-E95 -> 4792.1
B97: Income tax paid (net) | C97: 624.53 | D97: 940.73 | E97: 1088.26 | F97: Cash Flow Statement - FY26 AR p.124-125; FY25 AR p.114-115; FY24 AR p.118-119
B98: Capex - purchase of PPE and intangible assets | C98: 495.5 | D98: 954.29 | E98: 1049.53 | F98: Cash Flow Statement - FY26 AR p.124-125; FY25 AR p.114-115; FY24 AR p.118-119
B99: Proceeds from sale of PPE | C99: 14.04 | D99: 29.98 | E99: 71.8 | F99: Cash Flow Statement - FY26 AR p.124-125; FY25 AR p.114-115; FY24 AR p.118-119
B100: Proceeds from non-current borrowings | C100: 0 | D100: 247 | E100: 103 | F100: Cash Flow Statement - FY26 AR p.124-125; FY25 AR p.114-115; FY24 AR p.118-119
B101: Repayments of non-current borrowings | C101: 1104.98 | D101: 688.73 | E101: 379.6 | F101: Cash Flow Statement - FY26 AR p.124-125; FY25 AR p.114-115; FY24 AR p.118-119
B102: Proceeds from current borrowings | C102: 5993.94 | D102: 4695.02 | E102: 1111.72 | F102: Cash Flow Statement - FY26 AR p.124-125; FY25 AR p.114-115; FY24 AR p.118-119
B103: Repayments of current borrowings | C103: 5778.58 | D103: 5029.3 | E103: 1111.72 | F103: Cash Flow Statement - FY26 AR p.124-125; FY25 AR p.114-115; FY24 AR p.118-119
B104: Payment of lease liabilities | C104: 20.02 | D104: 59.33 | E104: 14.8 | F104: Cash Flow Statement - FY26 AR p.124-125; FY25 AR p.114-115; FY24 AR p.118-119
B105: Interest paid | C105: 246.11 | D105: 149.06 | E105: 93.64 | F105: Cash Flow Statement - FY26 AR p.124-125; FY25 AR p.114-115; FY24 AR p.118-119
B106: Dividend paid | C106: 763.39 | D106: 2040.77 | E106: 1835.42 | F106: Cash Flow Statement - FY26 AR p.124-125; FY25 AR p.114-115; FY24 AR p.118-119
...

Sheet Ratios
A1: Ashok Leyland Limited - Credit Ratios (Standalone, FY24-FY26)
A2: All cells are formulas linked to the 'Financials' and 'Debt_Analysis' sheets. 'Trend' compares FY26 with FY24: movement within ±2% is 'Stable'; direction judged against the 'Better if' column. Negative net debt = net cash.
B4: Ratio | C4: FY24 | D4: FY25 | E4: FY26 | F4: Better if | G4: Trend FY24→FY26 | H4: Definition / formula used
A5: 1. SCALE & PROFITABILITY
B6: Revenue from operations (₹ cr) | C6: =Financials!C6 -> 38367.03 | D6: =Financials!D6 -> 38752.74 | E6: =Financials!E6 -> 44007.03 | F6: Higher | G6: =IF(ABS(E6-C6)<=ABS(C6)*0.02,"Stable",IF((E6>C6)=(F6="Higher"),"Improving","Weakening")) -> Improving | H6: Statement of P&L
B7: Revenue growth (YoY) | C7: =Financials!C6/Financials!C111-1 -> 0.061500702 | D7: =Financials!D6/Financials!D111-1 -> 0.010053163 | E7: =Financials!E6/Financials!E111-1 -> 0.13558499 | F7: Higher | G7: =IF(ABS(E7-C7)<=ABS(C7)*0.02,"Stable",IF((E7>C7)=(F7="Higher"),"Improving","Weakening")) -> Improving | H7: Revenue / previous-year revenue - 1
B8: EBITDA (₹ cr) | C8: =Financials!C23 -> 4606.58 | D8: =Financials!D23 -> 4930.56 | E8: =Financials!E23 -> 5732.25 | F8: Higher | G8: =IF(ABS(E8-C8)<=ABS(C8)*0.02,"Stable",IF((E8>C8)=(F8="Higher"),"Improving","Weakening")) -> Improving | H8: Revenue - COGS - employee cost - other expenses
B9: EBITDA margin | C9: =Financials!C23/Financials!C6 -> 0.12006611 | D9: =Financials!D23/Financials!D6 -> 0.12723126 | E9: =Financials!E23/Financials!E6 -> 0.1302576 | F9: Higher | G9: =IF(ABS(E9-C9)<=ABS(C9)*0.02,"Stable",IF((E9>C9)=(F9="Higher"),"Improving","Weakening")) -> Improving | H9: EBITDA / Revenue
B10: PAT (₹ cr) | C10: =Financials!C20 -> 2617.87 | D10: =Financials!D20 -> 3303.29 | E10: =Financials!E20 -> 3565.53 | F10: Higher | G10: =IF(ABS(E10-C10)<=ABS(C10)*0.02,"Stable",IF((E10>C10)=(F10="Higher"),"Improving","Weakening")) -> Improving | H10: Profit for the year
B11: PAT margin | C11: =Financials!C20/Financials!C6 -> 0.068232282 | D11: =Financials!D20/Financials!D6 -> 0.085240166 | E11: =Financials!E20/Financials!E6 -> 0.081021828 | F11: Higher | G11: =IF(ABS(E11-C11)<=ABS(C11)*0.02,"Stable",IF((E11>C11)=(F11="Higher"),"Improving","Weakening")) -> Improving | H11: PAT / Revenue
B12: ROCE (pre-tax) | C12: =Financials!C25/(Financials!C61+Financials!C88) -> 0.35003155 | D12: =Financials!D25/(Financials!D61+Financials!D88) -> 0.32392729 | E12: =Financials!E25/(Financials!E61+Financials!E88) -> 0.35063592 | F12: Higher | G12: =IF(ABS(E12-C12)<=ABS(C12)*0.02,"Stable",IF((E12>C12)=(F12="Higher"),"Improving","Weakening")) -> Stable | H12: EBIT / (Net worth + Total debt), year-end
B13: ROE | C13: =Financials!C20/Financials!C61 -> 0.29713508 | D13: =Financials!D20/Financials!D61 -> 0.28677404 | E13: =Financials!E20/Financials!E61 -> 0.27189932 | F13: Higher | G13: =IF(ABS(E13-C13)<=ABS(C13)*0.02,"Stable",IF((E13>C13)=(F13="Higher"),"Improving","Weakening")) -> Weakening | H13: PAT / Year-end net worth
A15: 2. LEVERAGE & CAPITAL STRUCTURE
B16: Total debt incl. leases (₹ cr) | C16: =Financials!C88 -> 2299.4 | D16: =Financials!D88 -> 1481.72 | E16: =Financials!E88 -> 1195.04 | F16: Lower | G16: =IF(ABS(E16-C16)<=ABS(C16)*0.02,"Stable",IF((E16>C16)=(F16="Higher"),"Improving","Weakening")) -> Improving | H16: Borrowings (NC + current) + lease liabilities
B17: Net debt / (net cash) (₹ cr) | C17: =Financials!C88-Financials!C89 -> 108.47 | D17: =Financials!D88-Financials!D89 -> -4196.8 | E17: =Financials!E88-Financials!E89 -> -5855.76 | F17: Lower | G17: =IF(ABS(E17-C17)<=ABS(C17)*0.02,"Stable",IF((E17>C17)=(F17="Higher"),"Improving","Weakening")) -> Improving | H17: Total debt - unencumbered cash & liquid investments
B18: Total debt / Equity | C18: =Financials!C88/Financials!C61 -> 0.2609879 | D18: =Financials!D88/Financials!D61 -> 0.12863504 | E18: =Financials!E88/Financials!E61 -> 0.09113107 | F18: Lower | G18: =IF(ABS(E18-C18)<=ABS(C18)*0.02,"Stable",IF((E18>C18)=(F18="Higher"),"Improving","Weakening")) -> Improving | H18: Total debt / Net worth (matches company's own disclosed ratio: 0.26 / 0.13 / 0.09)
B19: Total debt / Tangible net worth | C19: =Financials!C88/Financials!C90 -> 0.30699231 | D19: =Financials!D88/Financials!D90 -> 0.14516164 | E19: =Financials!E88/Financials!E90 -> 0.10135721 | F19: Lower | G19: =IF(ABS(E19-C19)<=ABS(C19)*0.02,"Stable",IF((E19>C19)=(F19="Higher"),"Improving","Weakening")) -> Improving | H19: Total debt / TNW
B20: Net debt / Equity | C20: =(Financials!C88-Financials!C89)/Financials!C61 -> 0.012311628 | D20: =(Financials!D88-Financials!D89)/Financials!D61 -> -0.36434382 | E20: =(Financials!E88-Financials!E89)/Financials!E61 -> -0.44654713 | F20: Lower | G20: =IF(ABS(E20-C20)<=ABS(C20)*0.02,"Stable",IF((E20>C20)=(F20="Higher"),"Improving","Weakening")) -> Improving | H20: Negative value = net cash position
B21: TOL / TNW | C21: =Financials!C91/Financials!C90 -> 1.9761285 | D21: =Financials!D91/Financials!D90 -> 1.3722464 | E21: =Financials!E91/Financials!E90 -> 1.3129551 | F21: Lower | G21: =IF(ABS(E21-C21)<=ABS(C21)*0.02,"Stable",IF((E21>C21)=(F21="Higher"),"Improving","Weakening")) -> Improving | H21: Total outside liabilities / Tangible net worth (bank-style gearing)
B22: Total debt / EBITDA | C22: =Financials!C88/Financials!C23 -> 0.49915556 | D22: =Financials!D88/Financials!D23 -> 0.30051759 | E22: =Financials!E88/Financials!E23 -> 0.2084766 | F22: Lower | G22: =IF(ABS(E22-C22)<=ABS(C22)*0.02,"Stable",IF((E22>C22)=(F22="Higher"),"Improving","Weakening")) -> Improving | H22: Years of EBITDA needed to repay gross debt
B23: Net debt / EBITDA | C23: =(Financials!C88-Financials!C89)/Financials!C23 -> 0.023546753 | D23: =(Financials!D88-Financials!D89)/Financials!D23 -> -0.8511812 | E23: =(Financials!E88-Financials!E89)/Financials!E23 -> -1.0215465 | F23: Lower | G23: =IF(ABS(E23-C23)<=ABS(C23)*0.02,"Stable",IF((E23>C23)=(F23="Higher"),"Improving","Weakening")) -> Improving | H23: Negative = cash exceeds debt
A25: 3. DEBT SERVICING / COVERAGE
B26: Interest coverage (EBITDA / Finance cost) | C26: =Financials!C23/Financials!C14 -> 18.467688 | D26: =Financials!D23/Financials!D14 -> 22.730902 | E26: =Financials!E23/Financials!E14 -> 33.772757 | F26: Higher | G26: =IF(ABS(E26-C26)<=ABS(C26)*0.02,"Stable",IF((E26>C26)=(F26="Higher"),"Improving","Weakening")) -> Improving | H26: Uses reported finance cost, which includes non-cash unwinding of discount on provisions (conservative)
B27: EBITDA / Interest on borrowings | C27: =Financials!C23/Financials!C29 -> 23.910412 | D27: =Financials!D23/Financials!D29 -> 34.66123 | E27: =Financials!E23/Financials!E29 -> 62.791653 | F27: Higher | G27: =IF(ABS(E27-C27)<=ABS(C27)*0.02,"Stable",IF((E27>C27)=(F27="Higher"),"Improving","Weakening")) -> Improving | H27: EBITDA / gross interest expense on borrowings (before capitalisation)
B28: EBIT / Finance cost | C28: =Financials!C25/Financials!C14 -> 15.590002 | D28: =Financials!D25/Financials!D14 -> 19.414596 | E28: =Financials!E25/Financials!E14 -> 29.559064 | F28: Higher | G28: =IF(ABS(E28-C28)<=ABS(C28)*0.02,"Stable",IF((E28>C28)=(F28="Higher"),"Improving","Weakening")) -> Improving | H28: EBIT / reported finance cost
B29: DSCR (cash basis) | C29: =(Financials!C23-Financials!C97)/(Financials!C105+Financials!C101+Financials!C104) -> 2.9042528 | D29: =(Financials!D23-Financials!D97)/(Financials!D105+Financials!D101+Financials!D104) -> 4.447376 | E29: =(Financials!E23-Financials!E97)/(Financials!E105+Financials!E101+Financials!E104) -> 9.515593 | F29: Higher | G29: =IF(ABS(E29-C29)<=ABS(C29)*0.02,"Stable",IF((E29>C29)=(F29="Higher"),"Improving","Weakening")) -> Improving | H29: (EBITDA - tax paid) / (interest paid + long-term principal repaid + lease payments)
A31: 4. CASH FLOW
B32: CFO as reported (₹ cr) | C32: =Financials!C94 -> 2503.12 | D32: =Financials!D94 -> 7819.42 | E32: =Financials!E94 -> 4792.1 | F32: Higher | G32: =IF(ABS(E32-C32)<=ABS(C32)*0.02,"Stable",IF((E32>C32)=(F32="Higher"),"Improving","Weakening")) -> Improving | H32: Cash flow statement
B33: Adjusted CFO (₹ cr) | C33: =Financials!C96 -> 3956.6 | D33: =Financials!D96 -> 6365.94 | E33: =Financials!E96 -> 4792.1 | F33: Higher | G33: =IF(ABS(E33-C33)<=ABS(C33)*0.02,"Stable",IF((E33>C33)=(F33="Higher"),"Improving","Weakening")) -> Improving | H33: CFO excluding ₹1,453 cr interim-dividend account timing swing (FY24/FY25)
B34: Adjusted CFO / Total debt | C34: =Financials!C96/Financials!C88 -> 1.7207098 | D34: =Financials!D96/Financials!D88 -> 4.2963178 | E34: =Financials!E96/Financials!E88 -> 4.0099913 | F34: Higher | G34: =IF(ABS(E34-C34)<=ABS(C34)*0.02,"Stable",IF((E34>C34)=(F34="Higher"),"Improving","Weakening")) -> Improving | H34: Adjusted CFO / Total debt
B35: Capex (₹ cr) | C35: =Financials!C98 -> 495.5 | D35: =Financials!D98 -> 954.29 | E35: =Financials!E98 -> 1049.53 | F35: n.a. | G35: n.a. | H35: Purchase of PPE and intangibles
B36: Capex / Revenue | C36: =Financials!C98/Financials!C6 -> 0.012914734 | D36: =Financials!D98/Financials!D6 -> 0.024625097 | E36: =Financials!E98/Financials!E6 -> 0.023849144 | F36: n.a. | G36: n.a. | H36: Capital intensity
B37: Capex / D&A | C37: =Financials!C98/Financials!C15 -> 0.69029409 | D37: =Financials!D98/Financials!D15 -> 1.3266188 | E37: =Financials!E98/Financials!E15 -> 1.4674842 | F37: n.a. | G37: n.a. | H37: >1x means asset base is being expanded, not just maintained
B38: Free cash flow (Adj. CFO - Capex) (₹ cr) | C38: =Financials!C96-Financials!C98 -> 3461.1 | D38: =Financials!D96-Financials!D98 -> 5411.65 | E38: =Financials!E96-Financials!E98 -> 3742.57 | F38: Higher | G38: =IF(ABS(E38-C38)<=ABS(C38)*0.02,"Stable",IF((E38>C38)=(F38="Higher"),"Improving","Weakening")) -> Improving | H38: Adjusted CFO - capex
B39: FCF after dividends (₹ cr) | C39: =Financials!C96-Financials!C98-Financials!C106 -> 2697.71 | D39: =Financials!D96-Financials!D98-Financials!D106 -> 3370.88 | E39: =Financials!E96-Financials!E98-Financials!E106 -> 1907.15 | F39: Higher | G39: =IF(ABS(E39-C39)<=ABS(C39)*0.02,"Stable",IF((E39>C39)=(F39="Higher"),"Improving","Weakening")) -> Weakening | H39: FCF - dividends paid; negative = payouts funded from cash/borrowing
B40: Dividend paid / PAT | C40: =Financials!C106/Financials!C20 -> 0.2916073 | D40: =Financials!D106/Financials!D20 -> 0.61779922 | E40: =Financials!E106/Financials!E20 -> 0.51476779 | F40: n.a. | G40: n.a. | H40: Cash dividend (incl. FY24 interim paid in FY25) / PAT
A42: 5. LIQUIDITY
B43: Current ratio | C43: =Financials!C56/Financials!C78 -> 0.96334221 | D43: =Financials!D56/Financials!D78 -> 1.0772344 | E43: =Financials!E56/Financials!E78 -> 1.1002016 | F43: Higher | G43: =IF(ABS(E43-C43)<=ABS(C43)*0.02,"Stable",IF((E43>C43)=(F43="Higher"),"Improving","Weakening")) -> Improving | H43: Current assets / current liabilities
B44: Quick ratio | C44: =(Financials!C56-Financials!C48)/Financials!C78 -> 0.69829886 | D44: =(Financials!D56-Financials!D48)/Financials!D78 -> 0.81841358 | E44: =(Financials!E56-Financials!E48)/Financials!E78 -> 0.83861874 | F44: Higher | G44: =IF(ABS(E44-C44)<=ABS(C44)*0.02,"Stable",IF((E44>C44)=(F44="Higher"),"Improving","Weakening")) -> Improving | H44: (Current assets - inventory) / current liabilities
B45: Cash ratio | C45: =Financials!C89/Financials!C78 -> 0.18199557 | D45: =Financials!D89/Financials!D78 -> 0.49697667 | E45: =Financials!E89/Financials!E78 -> 0.5290756 | F45: Higher | G45: =IF(ABS(E45-C45)<=ABS(C45)*0.02,"Stable",IF((E45>C45)=(F45="Higher"),"Improving","Weakening")) -> Improving | H45: Unencumbered cash & liquid investments / current liabilities
B46: Unencumbered cash & liquid investments (₹ cr) | C46: =Financials!C89 -> 2190.93 | D46: =Financials!D89 -> 5678.52 | E46: =Financials!E89 -> 7050.8 | F46: Higher | G46: =IF(ABS(E46-C46)<=ABS(C46)*0.02,"Stable",IF((E46>C46)=(F46="Higher"),"Improving","Weakening")) -> Improving | H46: See Financials section E
B47: Liquidity cover of borrowings due in 12 months | C47: =(Financials!C89+Financials!C113)/Debt_Analysis!C41 -> 3.8196782 | D47: =(Financials!D89+Financials!D113)/Debt_Analysis!D41 -> 14.166116 | E47: =(Financials!E89+Financials!E113)/Debt_Analysis!E41 -> 14.197457 | F47: Higher | G47: =IF(ABS(E47-C47)<=ABS(C47)*0.02,"Stable",IF((E47>C47)=(F47="Higher"),"Improving","Weakening")) -> Improving | H47: (Unencumbered cash & liquid inv. + undrawn lines) / contractual borrowing outflow due within 1 year
A49: 6. WORKING CAPITAL (year-end balances)
B50: Inventory days | C50: =Financials!C48/Financials!C11*365 -> 41.724041 | D50: =Financials!D48/Financials!D11*365 -> 39.077233 | E50: =Financials!E48/Financials!E11*365 -> 40.5001 | F50: Lower | G50: =IF(ABS(E50-C50)<=ABS(C50)*0.02,"Stable",IF((E50>C50)=(F50="Higher"),"Improving","Weakening")) -> Improving | H50: Inventory / COGS x 365
B51: Receivable days | C51: =Financials!C50/Financials!C6*365 -> 33.959424 | D51: =Financials!D50/Financials!D6*365 -> 27.194769 | E51: =Financials!E50/Financials!E6*365 -> 24.471082 | F51: Lower | G51: =IF(ABS(E51-C51)<=ABS(C51)*0.02,"Stable",IF((E51>C51)=(F51="Higher"),"Improving","Weakening")) -> Improving | H51: Trade receivables / Revenue x 365
B52: Payable days | C52: =Financials!C85/Financials!C11*365 -> 82.45176 | D52: =Financials!D85/Financials!D11*365 -> 96.522213 | E52: =Financials!E85/Financials!E11*365 -> 96.768194 | F52: n.a. | G52: n.a. | H52: Trade payables / COGS x 365
B53: Cash conversion cycle | C53: =C50+C51-C52 -> -6.7682947 | D53: =D50+D51-D52 -> -30.250212 | E53: =E50+E51-E52 -> -31.797012 | F53: Lower | G53: =IF(ABS(E53-C53)<=ABS(C53)*0.02,"Stable",IF((E53>C53)=(F53="Higher"),"Improving","Weakening")) -> Improving | H53: Inventory days + receivable days - payable days
A55: 7. OFF-BALANCE SHEET & GROUP EXPOSURE
B56: Contingent liabilities / Net worth | C56: =Financials!C114/Financials!C61 -> 0.04020603 | D56: =Financials!D114/Financials!D61 -> 0.031970372 | E56: =Financials!E114/Financials!E61 -> 0.026146497 | F56: Lower | G56: =IF(ABS(E56-C56)<=ABS(C56)*0.02,"Stable",IF((E56>C56)=(F56="Higher"),"Improving","Weakening")) -> Improving | H56: Claims not acknowledged as debt / Net worth
B57: Corporate guarantees for group cos / Net worth | C57: =Financials!C115/Financials!C61 -> 0.08650715 | D57: =Financials!D115/Financials!D61 -> 0.088688135 | E57: =Financials!E115/Financials!E61 -> 0.059916483 | F57: Lower | G57: =IF(ABS(E57-C57)<=ABS(C57)*0.02,"Stable",IF((E57>C57)=(F57="Higher"),"Improving","Weakening")) -> Improving | H57: Guarantees for subsidiaries' loans / Net worth
B58: Non-current (group) investments / Net worth | C58: =Financials!C42/Financials!C61 -> 0.60277945 | D58: =Financials!D42/Financials!D61 -> 0.49087274 | E58: =Financials!E42/Financials!E61 -> 0.50019675 | F58: Lower | G58: =IF(ABS(E58-C58)<=ABS(C58)*0.02,"Stable",IF((E58>C58)=(F58="Higher"),"Improving","Weakening")) -> Improving | H58: Capital locked in subsidiaries/JVs (HLF, Switch, Optare etc.) relative to net worth
B59: Debt + guarantees / Equity | C59: =(Financials!C88+Financials!C115)/Financials!C61 -> 0.34749505 | D59: =(Financials!D88+Financials!D115)/Financials!D61 -> 0.21732317 | E59: =(Financials!E88+Financials!E115)/Financials!E61 -> 0.15104755 | F59: Lower | G59: =IF(ABS(E59-C59)<=ABS(C59)*0.02,"Stable",IF((E59>C59)=(F59="Higher"),"Improving","Weakening")) -> Improving | H59: Stress view: treats guarantees for subsidiaries as debt

Sheet Debt_Analysis
A1: Ashok Leyland Limited - Debt Composition, Maturity & Financial Risk (Standalone, ₹ crore)
A2: Blue = input from notes to accounts; Black = formula; Green = link to 'Financials' sheet.
B4: Particulars (₹ crore) | C4: FY24 | D4: FY25 | E4: FY26 | F4: Source / comment
A5: A. BORROWINGS BY INSTRUMENT (carrying value)
B6: Secured term loans from banks (non-current portion) | C6: 778.75 | D6: 636.48 | E6: 456.38 | F6: Note 1.16 - FY26 AR p.161; FY25 AR p.151
B7: Secured SIPCOT soft loan (non-current portion) | C7: 31.18 | D7: 0 | E7: 0 | F7: Note 1.16 - FY26 AR p.161; FY25 AR p.151 - fully repaid Jul-2025
B8: Secured NCDs - 7.30% AL 2027 (non-current portion) | C8: 199.33 | D8: 199.34 | E8: 0 | F8: Note 1.16 - FY26 AR p.161; FY25 AR p.151 - moved to current in FY26 (bullet 17-Mar-2027)
B9: Unsecured ECB from banks (non-current portion) | C9: 55.97 | D9: 0 | E9: 0 | F9: Note 1.16 - FY26 AR p.161; FY25 AR p.151 - ECB-16 fully repaid Nov-2025
B10: Unsecured interest-free sales tax loans (non-current) | C10: 66.41 | D10: 66.41 | E10: 61.5 | F10: Note 1.16 - FY26 AR p.161; FY25 AR p.151 - ends June 2028
B11: Non-current borrowings | C11: =SUM(C6:C10) -> 1131.64 | D11: =SUM(D6:D10) -> 902.23 | E11: =SUM(E6:E10) -> 517.88
B12: Secured short-term loans from banks | C12: 250 | D12: 0 | E12: 0 | F12: Note 1.21 - FY26 AR p.163; FY25 AR p.153
B13: Secured bills discounted | C13: 10.51 | D13: 0 | E13: 0 | F13: Note 1.21 - FY26 AR p.163; FY25 AR p.153
B14: Unsecured short-term loans from banks | C14: 150 | D14: 150 | E14: 150 | F14: Note 1.21 - FY26 AR p.163; FY25 AR p.153 - FY26: STL-29 @6.30%, due 25-Jun-2026 (Note 3.12)
B15: Unsecured bills discounted | C15: 73.8 | D15: 0 | E15: 0 | F15: Note 1.21 - FY26 AR p.163; FY25 AR p.153
B16: Current maturities of long-term debt - secured | C16: 304.69 | D16: 325.45 | E16: 478.91 | F16: Note 1.21 - FY26 AR p.163; FY25 AR p.153
B17: Current maturities of long-term debt - unsecured | C17: 333.89 | D17: 57.76 | E17: 4.91 | F17: Note 1.21 - FY26 AR p.163; FY25 AR p.153
B18: Current borrowings | C18: =SUM(C12:C17) -> 1122.89 | D18: =SUM(D12:D17) -> 533.21 | E18: =SUM(E12:E17) -> 633.82
B19: Total borrowings | C19: =C11+C18 -> 2254.53 | D19: =D11+D18 -> 1435.44 | E19: =E11+E18 -> 1151.7
B20: Check vs Balance Sheet total borrowings (0 = OK) | C20: =ROUND(C19-Financials!C87,2) -> 0 | D20: =ROUND(D19-Financials!D87,2) -> 0 | E20: =ROUND(E19-Financials!E87,2) -> 0
B21: Add: lease liabilities | C21: =Financials!C86 -> 44.87 | D21: =Financials!D86 -> 46.28 | E21: =Financials!E86 -> 43.34
B22: Total debt incl. leases | C22: =C19+C21 -> 2299.4 | D22: =D19+D21 -> 1481.72 | E22: =E19+E21 -> 1195.04
B23: Company-reported debt (capital-management note) | C23: 2299.4 | D23: 1481.72 | E23: 1195.04 | F23: Note 3.6.1 - FY26 AR p.183; FY25 AR p.171
B24: Check: our total debt - company-reported debt (0 = OK) | C24: =ROUND(C22-C23,2) -> 0 | D24: =ROUND(D22-D23,2) -> 0 | E24: =ROUND(E22-E23,2) -> 0
A26: B. DEBT MIX
B27: Secured borrowings | C27: =C6+C7+C8+C12+C13+C16 -> 1574.46 | D27: =D6+D7+D8+D12+D13+D16 -> 1161.27 | E27: =E6+E7+E8+E12+E13+E16 -> 935.29
B28: Unsecured borrowings | C28: =C9+C10+C14+C15+C17 -> 680.07 | D28: =D9+D10+D14+D15+D17 -> 274.17 | E28: =E9+E10+E14+E15+E17 -> 216.41
B29: Secured share of borrowings | C29: =C27/C19 -> 0.69835398 | D29: =D27/D19 -> 0.80899933 | E29: =E27/E19 -> 0.81209516
B30: Short-term debt (working-capital loans + bills) | C30: =SUM(C12:C15) -> 484.31 | D30: =SUM(D12:D15) -> 150 | E30: =SUM(E12:E15) -> 150
B31: Short-term debt share of borrowings | C31: =C30/C19 -> 0.21481639 | D31: =D30/D19 -> 0.10449758 | E31: =E30/E19 -> 0.13024225
B32: Variable-rate borrowings (principal) | C32: 358.75 | D32: 402 | E32: 403.13 | F32: Note 3.6.2(2) Interest-rate risk - FY26 AR p.186; FY25 AR p.174
B33: Fixed-rate borrowings (principal, incl. swapped) | C33: 1830.45 | D33: 967.69 | E33: 682.5 | F33: Note 3.6.2(2) - FY24 incl. ₹389.95 cr, FY25 ₹57.76 cr swapped to fixed
B34: Floating-rate share | C34: =C32/(C32+C33) -> 0.16387265 | D34: =D32/(D32+D33) -> 0.29349707 | E34: =E32/(E32+E33) -> 0.37133277
B35: Profit impact of +/-25 bp rate move (₹ cr, as disclosed) | C35: 0.45 | D35: 0.5 | E35: 1.01 | F35: Note 3.6.2(2)
B36: Weighted avg. interest rate - long-term loans | C36: 0.0754 | D36: 0.0722 | E36: 0.0683 | F36: Note 3.11 - FY26 AR p.203; FY25 AR p.190; FY24 AR p.189
B37: Weighted avg. interest rate - short-term borrowings | C37: 0.0739 | D37: 0.073 | E37: 0.063 | F37: Note 3.12
B38: Implied cost: gross interest / average total borrowings | C38: =Financials!C29/AVERAGE(Financials!C87,C97) -> 0.070900871 | D38: =Financials!D29/AVERAGE(Financials!D87,Financials!C87) -> 0.077100898 | E38: =Financials!E29/AVERAGE(Financials!E87,Financials!D87) -> 0.070572138 | F38: FY24 uses FY23 closing borrowings (₹3,180.10 cr, FY24 AR p.116) - see row below
A40: C. CONTRACTUAL MATURITY PROFILE (undiscounted cash flows incl. interest)
B41: Borrowings due within 1 year | C41: 1234.46 | D41: 614.03 | E41: 697.67 | F41: Note 3.6.2(C) Liquidity risk - FY26 AR p.188; FY25 AR p.176; FY24 AR p.176
B42: Borrowings due in years 2-5 | C42: 1252.74 | D42: 945.77 | E42: 558.53 | F42: Note 3.6.2(C) Liquidity risk - FY26 AR p.188; FY25 AR p.176; FY24 AR p.176
B43: Borrowings due after 5 years | C43: 0 | D43: 62.16 | E43: 16.91 | F43: Note 3.6.2(C) Liquidity risk - FY26 AR p.188; FY25 AR p.176; FY24 AR p.176
B44: Total contractual borrowing outflows | C44: =SUM(C41:C43) -> 2487.2 | D44: =SUM(D41:D43) -> 1621.96 | E44: =SUM(E41:E43) -> 1273.11
B45: Lease payments due within 1 year | C45: 19.2 | D45: 18.42 | E45: 18.31 | F45: Note 3.6.2(C) Liquidity risk - FY26 AR p.188; FY25 AR p.176; FY24 AR p.176
B46: Lease payments due in years 2-5 | C46: 26.97 | D46: 23.67 | E46: 25.85 | F46: Note 3.6.2(C) Liquidity risk - FY26 AR p.188; FY25 AR p.176; FY24 AR p.176
B47: Lease payments due after 5 years | C47: 26.39 | D47: 33.12 | E47: 35.16 | F47: Note 3.6.2(C) Liquidity risk - FY26 AR p.188; FY25 AR p.176; FY24 AR p.176
B48: % of borrowing outflows due within 1 year | C48: =C41/C44 -> 0.49632518 | D48: =D41/D44 -> 0.37857284 | E48: =E41/E44 -> 0.54800449
B49: % due in years 2-5 | C49: =C42/C44 -> 0.50367482 | D49: =D42/D44 -> 0.58310316 | E49: =E42/E44 -> 0.43871307
B50: % due after 5 years | C50: =C43/C44 -> 0 | D50: =D43/D44 -> 0.038324003 | E50: =E43/E44 -> 0.013282434
A52: D. REFINANCING & LIQUIDITY COVER
B53: Unencumbered cash & liquid investments | C53: =Financials!C89 -> 2190.93 | D53: =Financials!D89 -> 5678.52 | E53: =Financials!E89 -> 7050.8
B54: Undrawn committed bank lines | C54: =Financials!C113 -> 2524.31 | D54: =Financials!D113 -> 3019.9 | E54: =Financials!E113 -> 2854.34
B55: Commercial paper programme headroom (not counted in cover ratios) | C55: 2000 | D55: 2000 | E55: 2000 | F55: Note 3.6.2(C)
B56: Cash & liquid investments / debt due in 1 yr | C56: =C53/C41 -> 1.7748084 | D56: =D53/D41 -> 9.2479521 | E56: =E53/E41 -> 10.106211
B57: (Cash + undrawn lines) / debt due in 1 yr | C57: =(C53+C54)/C41 -> 3.8196782 | D57: =(D53+D54)/D41 -> 14.166116 | E57: =(E53+E54)/E41 -> 14.197457
B58: Adjusted CFO / debt due in 1 yr | C58: =Financials!C96/C41 -> 3.2051261 | D58: =Financials!D96/D41 -> 10.367474 | E58: =Financials!E96/E41 -> 6.8687202
B59: Cash & liquid investments / total debt | C59: =C53/C22 -> 0.95282682 | D59: =D53/D22 -> 3.832384 | E59: =E53/E22 -> 5.9000536
B60: Net debt / (net cash) | C60: =C22-C53 -> 108.47 | D60: =D22-D53 -> -4196.8 | E60: =E22-E53 -> -5855.76
A62: E. DEBT MOVEMENT DURING THE YEAR (cash flow)
B63: Long-term borrowings raised | C63: =Financials!C100 -> 0 | D63: =Financials!D100 -> 247 | E63: =Financials!E100 -> 103
B64: Long-term borrowings repaid | C64: =-Financials!C101 -> -1104.98 | D64: =-Financials!D101 -> -688.73 | E64: =-Financials!E101 -> -379.6
B65: Short-term borrowings - net | C65: =Financials!C102-Financials!C103 -> 215.36 | D65: =Financials!D102-Financials!D103 -> -334.28 | E65: =Financials!E102-Financials!E103 -> 0
B66: Net borrowing cash flow (negative = deleveraging) | C66: =SUM(C63:C65) -> -889.62 | D66: =SUM(D63:D65) -> -776.01 | E66: =SUM(E63:E65) -> -276.6
A68: F. CONTINGENT LIABILITIES, GUARANTEES & COMMITMENTS
B69: Sales tax / VAT / GST disputes | C69: 244.28 | D69: 260.03 | E69: 232.34 | F69: Note 3.9 - FY26 AR p.200; FY25 AR p.188; FY24 AR p.187
B70: Excise duty | C70: 9.2 | D70: 9.03 | E70: 8.92 | F70: Note 3.9 - FY26 AR p.200; FY25 AR p.188; FY24 AR p.187
B71: Service tax | C71: 59.81 | D71: 59.36 | E71: 24.06 | F71: Note 3.9 - FY26 AR p.200; FY25 AR p.188; FY24 AR p.187
B72: Customs duty | C72: 0.43 | D72: 0.43 | E72: 0.41 | F72: Note 3.9 - FY26 AR p.200; FY25 AR p.188; FY24 AR p.187
B73: Others | C73: 40.51 | D73: 39.41 | E73: 77.14 | F73: Note 3.9 - FY26 AR p.200; FY25 AR p.188; FY24 AR p.187
B74: Total contingent liabilities | C74: =SUM(C69:C73) -> 354.23 | D74: =SUM(D69:D73) -> 368.26 | E74: =SUM(E69:E73) -> 342.87
B75: Check vs Financials memo (0 = OK) | C75: =ROUND(C74-Financials!C114,2) -> 0 | D75: =ROUND(D74-Financials!D114,2) -> 0 | E75: =ROUND(E74-Financials!E114,2) -> 0
B76: Guarantee availed - Switch Mobility Ltd, UK | C76: 601.57 | D76: 891.9 | E76: 633.12 | F76: Note 3.9.1 - FY26 AR p.201; FY25 AR p.189
B77: Guarantee availed - Albonair GmbH | C77: 125.83 | D77: 128.93 | E77: 152.59 | F77: Note 3.9.1
B78: Guarantee availed - Optare plc, UK | C78: 31.51 | D78: 0 | E78: 0 | F78: Note 3.9.1
B79: Guarantee availed - Ashley Alteams India Ltd | C79: 3.25 | D79: 0.75 | E79: 0 | F79: Note 3.9.1
B80: Total guarantees availed (sum of above) | C80: =SUM(C76:C79) -> 762.16 | D80: =SUM(D76:D79) -> 1021.58 | E80: =SUM(E76:E79) -> 785.71 | F80: Ties to value of corporate guarantees in Note 3.9.2 (see next row)
B81: Corporate guarantee value per Note 3.9.2 | C81: =Financials!C115 -> 762.16 | D81: =Financials!D115 -> 1021.58 | E81: =Financials!E115 -> 785.71
B82: Capital commitments | C82: =Financials!C116 -> 467.57 | D82: =Financials!D116 -> 727.75 | E82: =Financials!E116 -> 460.19
B83: Total off-balance-sheet exposure (CL + guarantees + capex commitments) | C83: =C74+C81+C82 -> 1583.96 | D83: =D74+D81+D82 -> 2117.59 | E83: =E74+E81+E82 -> 1588.77
B84: Off-balance-sheet exposure / Net worth | C84: =C83/Financials!C61 -> 0.1797836 | D84: =D83/Financials!D61 -> 0.18383789 | E84: =E83/Financials!E61 -> 0.12115604
A86: G. FOREIGN-CURRENCY EXPOSURE (monetary items, ₹ crore equivalent)
B87: Gross FX liabilities (all currencies) | C87: 568.01 | D87: 212.19 | E87: 180.38 | F87: Note 3.6.2(1) - FY26 AR p.183-184; FY25 AR p.172 - sum of currency rows in note
B88: of which hedged with derivatives | C88: 437.3 | D88: 133.72 | E88: 55.73 | F88: Note 3.6.2(1) - FY26 AR p.183-184; FY25 AR p.172
B89: Hedge ratio on FX liabilities | C89: =C88/C87 -> 0.76988081 | D89: =D88/D87 -> 0.63018992 | E89: =E88/E87 -> 0.30895886
B90: Net overall USD exposure - net asset / (net liability) | C90: -67.03 | D90: -42.79 | E90: 168.62 | F90: Note 3.6.2(1) - FY26 AR p.183-184; FY25 AR p.172
B91: Net overall AED exposure | C91: 52.85 | D91: 54.04 | E91: 57.53 | F91: Note 3.6.2(1) - FY26 AR p.183-184; FY25 AR p.172
B92: Net overall exposure - EUR, GBP, JPY, SGD, others | C92: 8.27 | D92: -3.03 | E92: 2.12 | F92: Note 3.6.2(1) - FY26 AR p.183-184; FY25 AR p.172 - aggregated
B93: Net overall FX exposure | C93: =SUM(C90:C92) -> -5.91 | D93: =SUM(D90:D92) -> 8.22 | E93: =SUM(E90:E92) -> 228.27
B94: Impact of 2% INR move on net exposure (₹ cr) | C94: =ABS(C93)*2% -> 0.1182 | D94: =ABS(D93)*2% -> 0.1644 | E94: =ABS(E93)*2% -> 4.5654
B95: 2% impact as % of PAT | C95: =C94/Financials!C20 -> 4.5151211e-05 | D95: =D94/Financials!D20 -> 4.9768564e-05 | E95: =E94/Financials!E20 -> 0.0012804268
B97: FY23 closing total borrowings (for FY24 average) | C97: 3180.1 | F97: FY24 AR p.116: NC borrowings 1,766.23 + current 1,413.87
A99: H. FY26 INSTRUMENT-WISE DEBT & REPAYMENT TERMS (principal, Note 3.11 & 3.12, FY26 AR p.202-203)
B100: Instrument | C100: Non-current | D100: Due FY27 | E100: Total | F100: Repayment terms / security
B101: TL-12 | C101: 0 | D101: 100 | E101: =C101+D101 -> 100 | F101: 5 equal annual instalments from Sep-2022; charge on P&M at Pantnagar - fully due FY27
B102: TL-15 | C102: 37.5 | D102: 28.75 | E102: =C102+D102 -> 66.25 | F102: 20 quarterly instalments (varying) from Jul-2023; exclusive charge Pantnagar & Hosur (1.25x)
B103: TL-16 | C103: 80 | D103: 40 | E103: =C103+D103 -> 120 | F103: 5 equal annual instalments from Mar-2025; charge on P&M Chennai & Hosur
B104: TL-17 | C104: 56.25 | D104: 56.25 | E104: =C104+D104 -> 112.5 | F104: 12 semi-annual instalments (varying) from Sep-2022; charge on P&M Hosur (1.10x)
B105: TL-18 | C105: 282.63 | D105: 54.25 | E105: =C105+D105 -> 336.88 | F105: 24 quarterly instalments (varying) from Sep-2025; exclusive charge on aircraft
B106: NCD Series 3 (7.30% AL 2027) | C106: 0 | D106: 200 | E106: =C106+D106 -> 200 | F106: Bullet 17-Mar-2027; charge on P&M Hosur (1.10x); ₹100 cr FD kept for DRF
B107: Interest-free sales tax loan (Programme II) | C107: 61.5 | D107: 4.91 | E107: =C107+D107 -> 66.41 | F107: Varying periodic amounts ending June 2028; unsecured
B108: STL-29 (short-term, unsecured) | C108: 0 | D108: 150 | E108: =C108+D108 -> 150 | F108: Repayable 25-Jun-2026 @ 6.30%
B109: Total principal outstanding (31-Mar-2026) | C109: =SUM(C101:C108) -> 517.88 | D109: =SUM(D101:D108) -> 634.16 | E109: =SUM(E101:E108) -> 1152.04
...

Sheet Consolidated_View
A1: Why the analysis uses STANDALONE numbers - consolidated snapshot (₹ crore)
A2: Consolidated accounts include Hinduja Leyland Finance (an NBFC subsidiary). Its lending book is funded by borrowings, which swamps the vehicle business's debt. The assignment excludes NBFC-style analysis, so the core credit view is on standalone Ashok Leyland; group exposure is captured through investments and guarantees.
B4: Particulars | C4: FY24 | D4: FY25 | E4: FY26 | F4: Source
B5: Revenue from operations (ex-financing income) | C5: 40956.35 | D5: 42333.28 | E5: 48313.71 | F5: Consolidated BS/P&L - FY26 AR p.220-221; FY25 AR p.208-209
B6: Income from financing operations (HLF) | C6: 4746.99 | D6: 6201.86 | E6: 8048.37 | F6: Consolidated BS/P&L - FY26 AR p.220-221; FY25 AR p.208-209
B7: Finance costs | C7: 2982.25 | D7: 3930.21 | E7: 4704.65 | F7: Consolidated BS/P&L - FY26 AR p.220-221; FY25 AR p.208-209
B8: Profit for the year (incl. NCI) | C8: 2696.34 | D8: 3382.79 | E8: 3720.98 | F8: Consolidated BS/P&L - FY26 AR p.220-221; FY25 AR p.208-209
B9: Non-current borrowings | C9: 26695.71 | D9: 36382.92 | E9: 46016.36 | F9: Consolidated BS/P&L - FY26 AR p.220-221; FY25 AR p.208-209
B10: Current borrowings | C10: 13868.63 | D10: 13318.18 | E10: 17633.44 | F10: Consolidated BS/P&L - FY26 AR p.220-221; FY25 AR p.208-209
B11: Total consolidated borrowings | C11: =C9+C10 -> 40564.34 | D11: =D9+D10 -> 49701.1 | E11: =E9+E10 -> 63649.8 | F11: Formula
B12: Total equity (incl. NCI) | C12: 11814.59 | D12: 15844.86 | E12: 18546.24 | F12: Consolidated BS/P&L - FY26 AR p.220-221; FY25 AR p.208-209
B13: Consolidated borrowings / Equity | C13: =C11/C12 -> 3.4334107 | D13: =D11/D12 -> 3.1367333 | E13: =E11/E12 -> 3.4319517 | F13: Formula
B14: Standalone borrowings (for comparison) | C14: =Financials!C87 -> 2254.53 | D14: =Financials!D87 -> 1435.44 | E14: =Financials!E87 -> 1151.7 | F14: Link
B15: Standalone share of consolidated borrowings | C15: =C14/C11 -> 0.055579112 | D15: =D14/D11 -> 0.028881453 | E15: =E14/E11 -> 0.018094322 | F15: Formula
