Workbook

Sheet Questionnaire
A1: Assumption
B2: Value | D2: Time Horizon | E2: Risk-appropriate Mutual Fund Category | F2: Nifty 50 %
A3: Inflation | B3: 0.06 | D3: <= 3 years (Short-term) | E3: Debt: Liquid / Ultra Short Duration Fund | F3: 0
A4: Bank return | B4: 0.06 | D4: 5-15 years (Medium-term) | E4: Hybrid: Balanced Advantage (Medium risk) / Equity: Large & Mid Cap (High risk) | F4: 0.5
A5: Nifty 50 return | B5: 0.15 | D5: 15+ years (Long-term / Retirement) | E5: Solution-Oriented Retirement Fund, plan matched to risk profile | F5: 1
A7: QUESTIONNAIRE
A9: Basic field | B9: Options / details
A10: Name | B10: Respondent name
A11: Age | B11: Exact age
A12: Age group | B12: 20-30 / 30-40 / 40-50 / 50-60
A13: City | B13: Indian city context
A14: Salary range | B14: Below INR 8 LPA | C14: INR 8-12 LPA | D14: INR 12-18 LPA | E14: INR 18-25 LPA | F14: INR 25-40 LPA | G14: INR 40-60 LPA | H14: Above INR 60 LPA
A15: Short-term goal | B15: Optional goal based on respondent
A16: Medium-term goal | B16: Optional goal based on respondent
A17: Long term goal | B17: Optional goal based on respondent
A18: Retirement goal | B18: Compulsory for all respondents
A21: Question | B21: Option | C21: Points
A22: Under what age scale do you fall? | B22: Below 18 | C22: 5
B23: 18 to 45 | C23: 4
B24: 46 to 55 | C24: 3
B25: 56 to 65 | C25: 2
B26: 66 and above | C26: 1
A28: How much money can you take out of your monthly income for investment? | B28: 0 | C28: 1
B29: >0% <=10% | C29: 2
B30: >10% <=30% | C30: 3
B31: >30% <=50% | C31: 4
B32: >50% | C32: 5
A34: How familiar are you with stock market and concept of investment, risk and return? | B34: Not at all familiar | C34: 1
B35: Fairly familiar as I know how markets work and that stocks might be volatile and uncertain | C35: 3
B36: Very familiar as I know what to look out for before investing in any security | C36: 5
A38: How long have you been investing in stock markets? | B38: This is my first investment/Never before | C38: 1
B39: Been around 3 years | C39: 3
B40: More than 3 years | C40: 5
A42: Where do you prefer investing your money? | B42: Guaranteed income plans | C42: 1
B43: Steady growth plans | C43: 3
B44: Volatile plans with potential of very high returns | C44: 5
A46: How would you feel if the performance of your recent investments is below expectation? | B46: Panicked | C46: 1
B47: Quite uneasy | C47: 2
B48: A little concerned | C48: 3
B49: I will accept the possible highs and lows | C49: 4
B50: I will feel excited about the potential of gains | C50: 5
A52: Approximately what percentage of your funds are invested in volatile products? | B52: 0 | C52: 1
B53: >0% but <=10% | C53: 2
B54: >10% but <=30% | C54: 3
B55: >30% but <=50% | C55: 4
B56: >50% | C56: 5
A58: How much fluctuation in your investment would you normally be comfortable with? | B58: 0 | C58: 1
B59: Between -5% to +5% | C59: 2
B60: Between -10% to +10% | C60: 3
B61: Between -20% to +20% | C61: 4
B62: Even more | C62: 5
A64: What time period of investment are you more comfortable with? | B64: <=1 year | C64: 1
B65: >1 <=3 years | C65: 2
B66: >3 <=5 years | C66: 3
B67: >5 <=10 years | C67: 4
B68: >10 years | C68: 5
A70: What kind of return-risk relation will appeal most to you? | B70: Return up to 3% with no risk of negative returns | C70: 1
B71: Returns ranging from 3-5% p.a. with risk of negative returns every 10 years | C71: 2
B72: 5-8% p.a. with risk of negative returns every 7 years | C72: 3
B73: 8-10% p.a. with risk of negative returns every 4 years | C73: 4
B74: >10% p.a. with risk of negative returns <=3 years | C74: 5
A76: Which fund would you choose considering the gain and loss provided? | B76: Fund A | C76: 1
B77: Fund B | C77: 3
B78: Fund C | C78: 5
A80: Suppose the value of your investment falls by 15% over a short period. What will be your action? | B80: You will be scared and sell off all your investments | C80: 1
B81: You will sell off a portion and invest in a risk-free option | C81: 2
B82: You will sell off a portion and invest in another stock | C82: 3
B83: You will wait and hold considering fluctuations are part of investing | C83: 4
B84: You will invest more money considering the value will rise in future | C84: 5
A86: Theme | B86: Nishtha Dalal | C86: Kushagra Natani | D86: Priya Mehta | E86: Anuj Dalal
A87: Monthly investment capacity | B87: 3 | C87: 4 | D87: 4 | E87: 4
A88: Emergency readiness | B88: 3 | C88: 4 | D88: 5 | E88: 5
A89: Market knowledge | B89: 3 | C89: 4 | D89: 3 | E89: 3
A90: Investment experience | B90: 2 | C90: 4 | D90: 4 | E90: 5
A91: Preferred investment | B91: 3 | C91: 4 | D91: 3 | E91: 2
A92: Below-expectation return | B92: 3 | C92: 4 | D92: 3 | E92: 3
A93: Volatile exposure | B93: 2 | C93: 4 | D93: 2 | E93: 2
A94: Fluctuation comfort | B94: 3 | C94: 4 | D94: 3 | E94: 2
A95: Investment horizon | B95: 4 | C95: 5 | D95: 3 | E95: 2
A96: Risk-return choice | B96: 3 | C96: 4 | D96: 3 | E96: 2
A97: Fund selection | B97: 3 | C97: 4 | D97: 3 | E97: 2
A98: 15% fall response | B98: 3 | C98: 4 | D98: 3 | E98: 2
A99: Goal liquidity | B99: 4 | C99: 4 | D99: 3 | E99: 2
A100: Total Score | B100: =SUM(B87:B99) -> 39 | C100: =SUM(C87:C99) -> 53 | D100: =SUM(D87:D99) -> 42 | E100: =SUM(E87:E99) -> 36
A101: Risk Profile | B101: Medium | C101: High | D101: medium | E101: medium
A102: Mutual fund allocation
A103: Nifty 50 Allocation

Sheet Mutual Fund Selection
A1: Mutual Fund Selection - Detail & Rationale
A4: Persona | B4: Goal Type | C4: Goal | D4: Years | E4: Persona Risk Profile | F4: Selected Mutual Fund | G4: Category | H4: Fund Risk Appetite | I4: Expense Ratio | J4: AUM (INR Cr) | K4: 1Y Return | L4: 3Y Return | M4: 5Y Return | N4: Return % used for SIP | O4: Sharpe Ratio | P4: Monthly SIP INR
A5: Nishtha Dalal | B5: Short-term | C5: Postgraduate course fund | D5: 2 | E5: Medium | F5: HDFC Liquid Fund | G5: Debt - Liquid Fund | H5: Low | I5: 0.002 | J5: 67998.37 | K5: 0.0626 | L5: 0.0696 | M5: 0.0615 | N5: 0.0696 | O5: 0.0431 | P5: =Personas!L16 -> 17507.687
A6: Nishtha Dalal | B6: Medium-term | C6: Home purchase | D6: 10 | E6: Medium | F6: HDFC Balanced Advantage Fund | G6: Hybrid - Balanced Advantage | H6: Medium | I6: 0.0075 | J6: 104016.21 | K6: -0.0044 | L6: 0.1471 | M6: 0.1505 | N6: 0.1505 | O6: 0.0081 | P6: =Personas!L17 -> 11677.1
A7: Nishtha Dalal | B7: Long-term | C7: Retirement corpus | D7: 38 | E7: Medium | F7: Aditya Birla Sun Life Retirement Fund - The 30s Plan | G7: Solution-Oriented - Retirement Fund | H7: Mid | I7: 0.0114 | J7: 444.49 | K7: 0.094 | L7: 0.1781 | M7: 0.1227 | N7: 0.1227 | O7: 0.0077 | P7: =Personas!L18 -> 16448.222
A8: Kushagra Natani | B8: Short-term | C8: Home renovation | D8: 2 | E8: High | F8: ICICI Prudential Liquid Fund | G8: Debt - Liquid Fund | H8: Low | I8: 0.002 | J8: 58095.62 | K8: 0.0622 | L8: 0.0697 | M8: 0.0615 | N8: 0.0697 | O8: 0.0435 | P8: =Personas!L32 -> 39388.452
A9: Kushagra Natani | B9: Medium-term | C9: Home down payment | D9: 11 | E9: High | F9: ICICI Prudential Large & Mid Cap Fund | G9: Equity - Large & Mid Cap | H9: Very High | I9: 0.0076 | J9: 30146.91 | K9: 0.0023 | L9: 0.1814 | M9: 0.1762 | N9: 0.1762 | O9: 0.0087 | P9: =Personas!L33 -> 26210.026
A10: Kushagra Natani | B10: Long-term | C10: Retirement corpus | D10: 26 | E10: High | F10: Axis Retirement Fund - Dynamic Plan | G10: Solution-Oriented - Retirement Fund | H10: High | I10: 0.0129 | J10: 279.76 | K10: -0.0266 | L10: 0.1201 | M10: 0.1307 | N10: 0.1307 | O10: 0.0054 | P10: =Personas!L34 -> 55898.911
A11: Priya Mehta | B11: Short-term | C11: Child education fees | D11: 2 | E11: Medium | F11: Nippon India Liquid Fund | G11: Debt - Liquid Fund | H11: Low | I11: 0.002 | J11: 31752.32 | K11: 0.0629 | L11: 0.0701 | M11: 0.0619 | N11: 0.0701 | O11: 0.0458 | P11: =Personas!L48 -> 52497.441
A12: Priya Mehta | B12: Medium-term | C12: Child higher education fund | D12: 7 | E12: Medium | F12: SBI Balanced Advantage Fund | G12: Hybrid - Balanced Advantage | H12: Medium | I12: 0.0072 | J12: 40673.49 | K12: 0.0104 | L12: 0.1144 | N12: 0.1144 | O12: 0.0076 | P12: =Personas!L49 -> 52921.718
A13: Priya Mehta | B13: Long-term | C13: Retirement corpus | D13: 14 | E13: Medium | F13: SBI Retirement Benefit Fund - Aggressive Plan | G13: Solution-Oriented - Retirement Fund | H13: Medium | I13: 0.0093 | J13: 3000.31 | K13: -0.0521 | L13: 0.0938 | M13: 0.1258 | N13: 0.1258 | O13: 0.0035 | P13: =Personas!L50 -> 139237.83
A14: Anuj Dalal | B14: Short-term | C14: Medical contingency reserve | D14: 3 | E14: Medium | F14: ICICI Prudential Ultra Short Term Fund | G14: Debt - Ultra Short Duration | H14: Low | I14: 0.004 | J14: 16002.16 | K14: 0.0642 | L14: 0.074 | M14: 0.066 | N14: 0.074 | O14: 0.0337 | P14: =Personas!L62 -> 44473.094
A15: Anuj Dalal | B15: Medium-term | C15: Retirement transition fund | D15: 8 | E15: Medium | F15: ICICI Prudential Equity & Debt Fund | G15: Hybrid - Aggressive Hybrid | H15: Medium | I15: 0.0092 | J15: 50032.71 | K15: 0.0247 | L15: 0.1637 | M15: 0.1663 | N15: 0.1663 | O15: 0.0096 | P15: =Personas!L63 -> 80373.987
A16: Anuj Dalal | B16: Long-term | C16: Retirement safety corpus | D16: 8 | E16: Medium | F16: Tata Retirement Savings Fund - Moderate Plan | G16: Solution-Oriented - Retirement Fund | H16: Low | I16: 0.0068 | J16: 2145.42 | K16: -0.0124 | L16: 0.1374 | M16: 0.1151 | N16: 0.1151 | O16: 0.0065 | P16: =Personas!L64 -> 224173.68

Sheet Personas
A2: Assumption | B2: Value | D2: Time Horizon | E2: Risk-appropriate Mutual Fund Category | F2: Nifty 50 %
A3: Inflation | B3: 0.06 | D3: <= 3 years (Short-term) | E3: Debt: Liquid / Ultra Short Duration Fund | F3: 0
A4: Bank return | B4: 0.06 | D4: 5-15 years (Medium-term) | E4: Hybrid: Balanced Advantage (Medium risk) / Equity: Large & Mid Cap (High risk) | F4: 0.5
A5: Nifty 50 return | B5: 0.15 | D5: 15+ years (Long-term / Retirement) | E5: Solution-Oriented Retirement Fund, plan matched to risk profile | F5: 1
A7: Nishtha Dalal (20-30)
A8: Name | B8: Nishtha Dalal
A9: Age | B9: 22
A10: Age group | B10: 20-30
A11: City | B11: Mumbai
A12: Salary range | B12: INR 8-12 LPA
A13: Retirement goal | B13: Start early and build a retirement corpus by age 60.
A14: Risk profile | B14: Medium
A15: Goal type | B15: Goal | C15: Current age | D15: Target age | E15: Years | F15: Current cost INR | G15: Future cost INR | H15: Selected Mutual Fund | I15: Category | J15: Fund Risk Appetite | K15: Expected Return % | L15: Monthly SIP INR | M15: Why this fund
A16: Short-term | B16: Postgraduate course fund | C16: 22 | D16: 24 | E16: =D16-C16 -> 2 | F16: 400000 | G16: =FV($B$3,E16,0,-F16) -> 449440 | H16: HDFC Liquid Fund | I16: Debt - Liquid Fund | J16: Low | K16: 0.0696 | L16: =-PMT(K16/12,E16*12,0,G16,0) -> 17507.687 | M16: Capital safety for a 2-yr goal; near-term money kept out of market volatility.
A17: Medium-term | B17: home purchase | C17: 22 | D17: 32 | E17: =D17-C17 -> 10 | F17: 1800000 | G17: =FV($B$3,E17,0,-F17) -> 3223525.9 | H17: HDFC Balanced Advantage Fund | I17: Hybrid - Balanced Advantage | J17: Medium | K17: 0.1505 | L17: =-PMT(K17/12,E17*12,0,G17,0) -> 11677.1 | M17: Medium-risk hybrid fund balances equity growth with downside cushioning over 10 yrs.
A18: Long-term | B18: Retirement corpus | C18: 22 | D18: 60 | E18: =D18-C18 -> 38 | F18: 18000000 | G18: =FV($B$3,E18,0,-F18) -> 1.6477654e+08 | H18: Aditya Birla Sun Life Retirement Fund - The 30s Plan | I18: Solution-Oriented - Retirement Fund | J18: Mid | K18: 0.1227 | L18: =-PMT(K18/12,E18*12,0,G18,0) -> 16448.222 | M18: Equity-biased retirement plan suited to a young investor's 38-yr runway.
K20: Total | L20: =SUM(L16:L18) -> 45633.009
A23: Kushagra Natani(30-40)
A24: Name | B24: Kushagra Natani
A25: Age | B25: 34
A26: Age group | B26: 30-40
A27: City | B27: Indore
A28: Salary range | B28: INR 18-25 LPA
A29: Retirement goal | B29: Create financial independence by age 60.
A30: Risk profile | B30: High
A31: Goal type | B31: Goal | C31: Current age | D31: Target age | E31: Years | F31: Current cost INR | G31: Future cost INR | H31: Selected Mutual Fund | I31: Category | J31: Fund Risk Appetite | K31: Expected Return % | L31: Monthly SIP INR | M31: Why this fund
A32: Short-term | B32: Home renovation | C32: 34 | D32: 36 | E32: =D32-C32 -> 2 | F32: 900000 | G32: =FV($B$3,E32,0,-F32) -> 1011240 | H32: ICICI Prudential Liquid Fund | I32: Debt - Liquid Fund | J32: Low | K32: 0.0697 | L32: =-PMT(K32/12,E32*12,0,G32,0) -> 39388.452 | M32: Capital safety for a 2-yr goal; near-term money kept out of market volatility.
A33: Medium-term | B33: Home down payment | C33: 34 | D33: 45 | E33: =D33-C33 -> 11 | F33: 5500000 | G33: =FV($B$3,E33,0,-F33) -> 10440642 | H33: ICICI Prudential Large & Mid Cap Fund | I33: Equity - Large & Mid Cap | J33: Very High | K33: 0.1762 | L33: =-PMT(K33/12,E33*12,0,G33,0) -> 26210.026 | M33: High risk appetite + 11-yr horizon supports a pure-equity large & mid cap allocation.
A34: Long-term | B34: Retirement corpus | C34: 34 | D34: 60 | E34: =D34-C34 -> 26 | F34: 32000000 | G34: =FV($B$3,E34,0,-F34) -> 1.4558025e+08 | H34: Axis Retirement Fund - Dynamic Plan | I34: Solution-Oriented - Retirement Fund | J34: High | K34: 0.1307 | L34: =-PMT(K34/12,E34*12,0,G34,0) -> 55898.911 | M34: Aggressive retirement plan matching a high risk profile and 26-yr horizon.
K36: Total | L36: =SUM(L32:L34) -> 121497.39
A39: Priya Mehta (40-50)
A40: Name | B40: Priya Mehta
A41: Age | B41: 46
A42: Age group | B42: 40-50
A43: City | B43: Delhi NCR
A44: Salary range | B44: INR 25-40 LPA
A45: Retirement goal | B45: Protect retirement comfort while funding child's education.
A46: Risk profile | B46: Medium
A47: Goal type | B47: Goal | C47: Current age | D47: Target age | E47: Years | F47: Current cost INR | G47: Future cost INR | H47: Selected Mutual Fund | I47: Category | J47: Fund Risk Appetite | K47: Expected Return % | L47: Monthly SIP INR | M47: Why this fund
A48: Short-term | B48: Child education fees | C48: 46 | D48: 48 | E48: =D48-C48 -> 2 | F48: 1200000 | G48: =FV($B$3,E48,0,-F48) -> 1348320 | H48: Nippon India Liquid Fund | I48: Debt - Liquid Fund | J48: Low | K48: 0.0701 | L48: =-PMT(K48/12,E48*12,0,G48,0) -> 52497.441 | M48: Capital safety for a 2-yr goal; near-term money kept out of market volatility.
A49: Medium-term | B49: Child higher education fund | C49: 46 | D49: 53 | E49: =D49-C49 -> 7 | F49: 4500000 | G49: =FV($B$3,E49,0,-F49) -> 6766336.2 | H49: SBI Balanced Advantage Fund | I49: Hybrid - Balanced Advantage | J49: Medium | K49: 0.1144 | L49: =-PMT(K49/12,E49*12,0,G49,0) -> 52921.718 | M49: Medium-risk hybrid fund cushions volatility while still growing a 7-yr education corpus.
A50: Long-term | B50: Retirement corpus | C50: 46 | D50: 60 | E50: =D50-C50 -> 14 | F50: 28000000 | G50: =FV($B$3,E50,0,-F50) -> 63305311 | H50: SBI Retirement Benefit Fund - Aggressive Plan | I50: Solution-Oriented - Retirement Fund | J50: Medium | K50: 0.1258 | L50: =-PMT(K50/12,E50*12,0,G50,0) -> 139237.83 | M50: Growth-oriented retirement plan fitting a medium risk profile over a 14-yr horizon.
K52: Total | L52: =SUM(L48:L50) -> 244656.99
A53: Anuj Dalal (50-60)
A54: Name | B54: Anuj Dalal
A55: Age | B55: 52
A56: Age group | B56: 50-60
A57: City | B57: kota
A58: Salary range | B58: INR 40-60 LPA
A59: Retirement goal | B59: Shift toward stable retirement income by age 60.
A60: Risk profile | B60: Medium
A61: Goal type | B61: Goal | C61: Current age | D61: Target age | E61: Years | F61: Current cost INR | G61: Future cost INR | H61: Selected Mutual Fund | I61: Category | J61: Fund Risk Appetite | K61: Expected Return % | L61: Monthly SIP INR | M61: Why this fund
A62: Short-term | B62: Medical contingency reserve | C62: 52 | D62: 55 | E62: =D62-C62 -> 3 | F62: 1500000 | G62: =FV($B$3,E62,0,-F62) -> 1786524 | H62: ICICI Prudential Ultra Short Term Fund | I62: Debt - Ultra Short Duration | J62: Low | K62: 0.074 | L62: =-PMT(K62/12,E62*12,0,G62,0) -> 44473.094 | M62: Slightly longer 3-yr horizon than a pure liquid fund; still capital-protection focused.
A63: Medium-term | B63: Retirement transition fund | C63: 52 | D63: 60 | E63: =D63-C63 -> 8 | F63: 10000000 | G63: =FV($B$3,E63,0,-F63) -> 15938481 | H63: ICICI Prudential Equity & Debt Fund | I63: Hybrid - Aggressive Hybrid | J63: Medium | K63: 0.1663 | L63: =-PMT(K63/12,E63*12,0,G63,0) -> 80373.987 | M63: Growth-tilted hybrid fund to actively build the transition corpus over 8 yrs.
A64: Long-term | B64: Retirement safety corpus | C64: 52 | D64: 60 | E64: =D64-C64 -> 8 | F64: 22000000 | G64: =FV($B$3,E64,0,-F64) -> 35064658 | H64: Tata Retirement Savings Fund - Moderate Plan | I64: Solution-Oriented - Retirement Fund | J64: Low | K64: 0.1151 | L64: =-PMT(K64/12,E64*12,0,G64,0) -> 224173.68 | M64: Lower-volatility retirement plan for the 'safety' corpus as retirement nears.
K66: Total | L66: =SUM(L62:L64) -> 349020.76
